dante_cluster_tracker/__init__.py
dante_cluster_tracker/dante.py
dante_cluster_tracker-0.0.2.dist-info/LICENSE
dante_cluster_tracker-0.0.2.dist-info/METADATA
dante_cluster_tracker-0.0.2.dist-info/WHEEL
dante_cluster_tracker-0.0.2.dist-info/top_level.txt
dante_cluster_tracker-0.0.2.dist-info/RECORD
