Metadata-Version: 2.1
Name: dante-cluster-tracker
Version: 0.0.2
Summary: Dante Package
Home-page: https://github.com/pypa/dante
Author: jpschuma
Author-email: jpschuma@arista.com
License: UNKNOWN
Project-URL: Bug Tracker, https://github.com/pypa/dante/issues
Platform: UNKNOWN
Classifier: Programming Language :: Python :: 3
Classifier: License :: OSI Approved :: MIT License
Classifier: Operating System :: OS Independent
Requires-Python: >=3.6
License-File: LICENSE
